nonebot/adapters/mirai/__init__.py
nonebot/adapters/mirai/adapter.py
nonebot/adapters/mirai/bot.py
nonebot/adapters/mirai/compat.py
nonebot/adapters/mirai/config.py
nonebot/adapters/mirai/event.py
nonebot/adapters/mirai/exception.py
nonebot/adapters/mirai/message.py
nonebot/adapters/mirai/model/__init__.py
nonebot/adapters/mirai/model/base.py
nonebot/adapters/mirai/model/common.py
nonebot/adapters/mirai/model/relationship.py
nonebot/adapters/mirai/utils.py
nonebot_adapter_mirai-2.3.3.dist-info/METADATA
nonebot_adapter_mirai-2.3.3.dist-info/WHEEL
nonebot_adapter_mirai-2.3.3.dist-info/licenses/LICENSE
nonebot_adapter_mirai-2.3.3.dist-info/RECORD
