Metadata-Version: 2.1
Name: nonebot-adapter-mirai
Version: 2.3.3
Summary: Mirai Api HTTP adapter for nonebot2
Keywords: bot,qq,qqbot,mirai
Home-page: https://nonebot.dev/
Author-Email: rf_tar_railt <rf_tar_railt@qq.com>, Mix <admin@yami.im>, yanyongyu <yyy@nonebot.dev>
License: AGPL-3.0-or-later
Classifier: Development Status :: 5 - Production/Stable
Classifier: Framework :: Robot Framework
Classifier: Framework :: Robot Framework :: Library
Classifier: Operating System :: OS Independent
Classifier: Programming Language :: Python :: 3.9
Classifier: Programming Language :: Python :: 3.10
Classifier: Programming Language :: Python :: 3.11
Classifier: Programming Language :: Python :: 3.12
Project-URL: Homepage, https://nonebot.dev/
Project-URL: Repository, https://github.com/nonebot/adapter-mirai
Project-URL: Documentation, https://nonebot.dev/
Requires-Python: <4.0.0,>=3.9.0
Requires-Dist: nonebot2>=2.3.0
